marshmallow_custom/__init__.py
marshmallow_custom/base.py
marshmallow_custom/class_registry.py
marshmallow_custom/compat.py
marshmallow_custom/decorators.py
marshmallow_custom/exceptions.py
marshmallow_custom/fields.py
marshmallow_custom/marshalling.py
marshmallow_custom/ordereddict.py
marshmallow_custom/orderedset.py
marshmallow_custom/schema.py
marshmallow_custom/utils.py
marshmallow_custom/validate.py
marshmallow_custom-1.0.2.dist-info/LICENSE
marshmallow_custom-1.0.2.dist-info/METADATA
marshmallow_custom-1.0.2.dist-info/WHEEL
marshmallow_custom-1.0.2.dist-info/top_level.txt
marshmallow_custom-1.0.2.dist-info/RECORD
